energyCnV/__init__.py
energyCnV/energy.py
energycnv-2.1.4.dist-info/METADATA
energycnv-2.1.4.dist-info/WHEEL
energycnv-2.1.4.dist-info/top_level.txt
energycnv-2.1.4.dist-info/RECORD
