Metadata-Version: 2.4
Name: energyCnV
Version: 2.1.4
Summary: Track and visualize GPU energy consumption using PyNVML, with MongoDB integration.
Home-page: https://github.com/siddhartha276/energyCnV
Author: VIT College
Author-email: siddhartha2706@gmail.com
Classifier: Programming Language :: Python :: 3
Classifier: License :: OSI Approved :: MIT License
Classifier: Operating System :: OS Independent
Classifier: Topic :: Scientific/Engineering :: Visualization
Requires-Python: >=3.6
Requires-Dist: nvidia-ml-py3
Requires-Dist: pymongo
Requires-Dist: bcrypt
Requires-Dist: dotenv
Requires-Dist: dnspython
Dynamic: author
Dynamic: author-email
Dynamic: classifier
Dynamic: description
Dynamic: description-content-type
Dynamic: home-page
Dynamic: requires-dist
Dynamic: requires-python
Dynamic: summary
